odoo/addons/sale_report_delivered_partner_priority/README.rst
odoo/addons/sale_report_delivered_partner_priority/__init__.py
odoo/addons/sale_report_delivered_partner_priority/__manifest__.py
odoo/addons/sale_report_delivered_partner_priority/i18n/es.po
odoo/addons/sale_report_delivered_partner_priority/i18n/it.po
odoo/addons/sale_report_delivered_partner_priority/i18n/sale_report_delivered_partner_priority.pot
odoo/addons/sale_report_delivered_partner_priority/models/__init__.py
odoo/addons/sale_report_delivered_partner_priority/models/sale_report_delivered.py
odoo/addons/sale_report_delivered_partner_priority/readme/CONTRIBUTORS.md
odoo/addons/sale_report_delivered_partner_priority/readme/DESCRIPTION.md
odoo/addons/sale_report_delivered_partner_priority/readme/USAGE.md
odoo/addons/sale_report_delivered_partner_priority/static/description/icon.png
odoo/addons/sale_report_delivered_partner_priority/static/description/index.html
odoo/addons/sale_report_delivered_partner_priority/views/sale_report_delivered_views.xml
odoo_addon_sale_report_delivered_partner_priority-18.0.1.0.0.4.dist-info/METADATA
odoo_addon_sale_report_delivered_partner_priority-18.0.1.0.0.4.dist-info/WHEEL
odoo_addon_sale_report_delivered_partner_priority-18.0.1.0.0.4.dist-info/top_level.txt
odoo_addon_sale_report_delivered_partner_priority-18.0.1.0.0.4.dist-info/RECORD
